hillfit/__init__.py
hillfit/fitting.py
test/__init__.py
test/test_fitting.py
hillfit-0.1.7.dist-info/LICENSE
hillfit-0.1.7.dist-info/METADATA
hillfit-0.1.7.dist-info/WHEEL
hillfit-0.1.7.dist-info/top_level.txt
hillfit-0.1.7.dist-info/RECORD
