Metadata-Version: 2.1
Name: hillfit
Version: 0.1.7
Summary: Model for fitting data with the Hill equation, and exporting the contents
Home-page: https://github.com/himoto/hillfit
Author: Andrew Freiburger, Hiroaki Imoto
Author-email: andrewfreiburger@gmail.com
License: MIT
Keywords: biochemistry,systems biology,computational biology,data science,Hill equation
Classifier: Intended Audience :: Science/Research
Classifier: License :: OSI Approved :: MIT License
Classifier: Operating System :: OS Independent
Classifier: Programming Language :: Python :: 3.7
Classifier: Programming Language :: Python :: 3.8
Classifier: Programming Language :: Python :: 3.9
License-File: LICENSE
Requires-Dist: matplotlib
Requires-Dist: numpy
Requires-Dist: pandas
Requires-Dist: scipy
Requires-Dist: scikit-learn
Requires-Dist: sigfig
